kinemotion/__init__.py
kinemotion/api.py
kinemotion/cli.py
kinemotion/core/__init__.py
kinemotion/core/auto_tuning.py
kinemotion/core/cli_utils.py
kinemotion/core/debug_overlay_utils.py
kinemotion/core/determinism.py
kinemotion/core/experimental.py
kinemotion/core/filtering.py
kinemotion/core/formatting.py
kinemotion/core/metadata.py
kinemotion/core/model_downloader.py
kinemotion/core/overlay_constants.py
kinemotion/core/pipeline_utils.py
kinemotion/core/pose.py
kinemotion/core/pose_landmarks.py
kinemotion/core/quality.py
kinemotion/core/smoothing.py
kinemotion/core/timing.py
kinemotion/core/types.py
kinemotion/core/validation.py
kinemotion/core/video_analysis_base.py
kinemotion/core/video_io.py
kinemotion/countermovement_jump/__init__.py
kinemotion/countermovement_jump/analysis.py
kinemotion/countermovement_jump/api.py
kinemotion/countermovement_jump/cli.py
kinemotion/countermovement_jump/debug_overlay.py
kinemotion/countermovement_jump/joint_angles.py
kinemotion/countermovement_jump/kinematics.py
kinemotion/countermovement_jump/metrics_validator.py
kinemotion/countermovement_jump/validation_bounds.py
kinemotion/drop_jump/__init__.py
kinemotion/drop_jump/analysis.py
kinemotion/drop_jump/api.py
kinemotion/drop_jump/cli.py
kinemotion/drop_jump/debug_overlay.py
kinemotion/drop_jump/kinematics.py
kinemotion/drop_jump/metrics_validator.py
kinemotion/drop_jump/validation_bounds.py
kinemotion/models/__init__.py
kinemotion/models/pose_landmarker_lite.task
kinemotion/models/rtmpose-s_simcc-body7_pt-body7-halpe26_700e-256x192-7f134165_20230605.onnx
kinemotion/models/yolox_tiny_8xb8-300e_humanart-6f3252f9.onnx
kinemotion/squat_jump/__init__.py
kinemotion/squat_jump/analysis.py
kinemotion/squat_jump/api.py
kinemotion/squat_jump/cli.py
kinemotion/squat_jump/debug_overlay.py
kinemotion/squat_jump/kinematics.py
kinemotion/squat_jump/metrics_validator.py
kinemotion/squat_jump/validation_bounds.py
kinemotion/py.typed
kinemotion-0.76.2.dist-info/METADATA
kinemotion-0.76.2.dist-info/WHEEL
kinemotion-0.76.2.dist-info/entry_points.txt
kinemotion-0.76.2.dist-info/licenses/LICENSE
kinemotion-0.76.2.dist-info/RECORD
