Metadata-Version: 2.4
Name: kinemotion
Version: 0.76.2
Summary: Video-based kinematic analysis for athletic performance
Project-URL: Homepage, https://github.com/feniix/kinemotion
Project-URL: Repository, https://github.com/feniix/kinemotion
Project-URL: Source, https://github.com/feniix/kinemotion
Project-URL: Issues, https://github.com/feniix/kinemotion/issues
Author-email: Sebastian Otaegui <feniix@gmail.com>
License: MIT
License-File: LICENSE
Keywords: athletic-performance,drop-jump,kinemetry,kinemotion,mediapipe,pose-tracking,video-analysis
Classifier: Development Status :: 3 - Alpha
Classifier: Intended Audience :: Science/Research
Classifier: License :: OSI Approved :: MIT License
Classifier: Programming Language :: Python :: 3
Classifier: Programming Language :: Python :: 3.10
Classifier: Programming Language :: Python :: 3.11
Classifier: Programming Language :: Python :: 3.12
Classifier: Topic :: Multimedia :: Video
Classifier: Topic :: Scientific/Engineering :: Image Recognition
Requires-Python: <3.13,>=3.10
Requires-Dist: click>=8.1.7
Requires-Dist: mediapipe>=0.10.30
Requires-Dist: numpy>=1.26.0
Requires-Dist: opencv-python>=4.9.0
Requires-Dist: platformdirs>=4.0.0
Requires-Dist: scipy>=1.11.0
Requires-Dist: tqdm>=4.67.1
Requires-Dist: typing-extensions>=4.15.0
